wbfdm/__init__.py
wbfdm/apps.py
wbfdm/dynamic_preferences_registry.py
wbfdm/enums.py
wbfdm/jinja2.py
wbfdm/menu.py
wbfdm/preferences.py
wbfdm/signals.py
wbfdm/tasks.py
wbfdm/urls.py
wbfdm/utils.py
wbfdm/admin/__init__.py
wbfdm/admin/classifications.py
wbfdm/admin/esg.py
wbfdm/admin/exchanges.py
wbfdm/admin/instrument_lists.py
wbfdm/admin/instrument_prices.py
wbfdm/admin/instrument_requests.py
wbfdm/admin/instruments.py
wbfdm/admin/instruments_relationships.py
wbfdm/admin/options.py
wbfdm/analysis/__init__.py
wbfdm/analysis/utils.py
wbfdm/analysis/esg/__init__.py
wbfdm/analysis/esg/enums.py
wbfdm/analysis/esg/esg_analysis.py
wbfdm/analysis/esg/utils.py
wbfdm/analysis/financial_analysis/__init__.py
wbfdm/analysis/financial_analysis/financial_metric_analysis.py
wbfdm/analysis/financial_analysis/financial_ratio_analysis.py
wbfdm/analysis/financial_analysis/financial_statistics_analysis.py
wbfdm/analysis/financial_analysis/statement_with_estimates.py
wbfdm/analysis/financial_analysis/utils.py
wbfdm/analysis/technical_analysis/__init__.py
wbfdm/analysis/technical_analysis/technical_analysis.py
wbfdm/analysis/technical_analysis/traces.py
wbfdm/backends/dto.py
wbfdm/contrib/__init__.py
wbfdm/contrib/dsws/__init__.py
wbfdm/contrib/dsws/client.py
wbfdm/contrib/dsws/dataloaders/market_data.py
wbfdm/contrib/internal/__init__.py
wbfdm/contrib/internal/dataloaders/__init__.py
wbfdm/contrib/internal/dataloaders/market_data.py
wbfdm/contrib/metric/__init__.py
wbfdm/contrib/metric/apps.py
wbfdm/contrib/metric/decorators.py
wbfdm/contrib/metric/dispatch.py
wbfdm/contrib/metric/dto.py
wbfdm/contrib/metric/exceptions.py
wbfdm/contrib/metric/factories.py
wbfdm/contrib/metric/filters.py
wbfdm/contrib/metric/models.py
wbfdm/contrib/metric/orchestrators.py
wbfdm/contrib/metric/registry.py
wbfdm/contrib/metric/serializers.py
wbfdm/contrib/metric/tasks.py
wbfdm/contrib/metric/urls.py
wbfdm/contrib/metric/admin/__init__.py
wbfdm/contrib/metric/admin/instruments.py
wbfdm-2.2.6.dist-info/METADATA
wbfdm-2.2.6.dist-info/WHEEL
wbfdm-2.2.6.dist-info/RECORD
