Metadata-Version: 2.4
Name: wbfdm
Version: 2.2.6
Summary: The workbench module ensures rapid access to diverse financial data (market, fundamental, forecasts, ESG), with features for storing instruments, classifying them, and conducting financial analysis.
Author-email: Christopher Wittlinger <c.wittlinger@stainly.com>
Requires-Dist: roman==4.*
Requires-Dist: stockstats==0.6.*
Requires-Dist: wbcore
Requires-Dist: wbnews
Provides-Extra: dsws
Requires-Dist: datastreampy==2.0.*; extra == 'dsws'
Requires-Dist: requests-cache==1.0.*; extra == 'dsws'
Provides-Extra: qa
Requires-Dist: jinjasql2==0.1.*; extra == 'qa'
Requires-Dist: mssql-django==1.4.*; extra == 'qa'
